datagen/__init__.py
datagen/generator.py
datagen/db/__init__.py
datagen/db/mysql.py
datagen/maker/__init__.py
datagen/maker/dtype.py
datagen/maker/maker.py
datagen/maker/unique.py
datapush/__init__.py
datapush/generator.py
datapush/db/__init__.py
datapush/db/mysql.py
datapush/maker/__init__.py
datapush/maker/dtype.py
datapush/maker/maker.py
datapush/maker/unique.py
datapush-1.0.1.dist-info/LICENSE
datapush-1.0.1.dist-info/METADATA
datapush-1.0.1.dist-info/WHEEL
datapush-1.0.1.dist-info/top_level.txt
datapush-1.0.1.dist-info/RECORD
